_hydrogenlib_core/__about__.py
_hydrogenlib_core/__init__.py
_hydrogenlib_core/async_methods.py
_hydrogenlib_core/atexit.py
_hydrogenlib_core/const.py
_hydrogenlib_core/dataclasses_methods.py
_hydrogenlib_core/decorators.py
_hydrogenlib_core/descriptor.py
_hydrogenlib_core/environ_parser.py
_hydrogenlib_core/hash.py
_hydrogenlib_core/import_plus.py
_hydrogenlib_core/io_addons.py
_hydrogenlib_core/network.py
_hydrogenlib_core/nio.py
_hydrogenlib_core/output_methods.py
_hydrogenlib_core/process.py
_hydrogenlib_core/runtime.py
_hydrogenlib_core/time_.py
_hydrogenlib_core/trasyncio.py
_hydrogenlib_core/data_structures/__init__.py
_hydrogenlib_core/data_structures/b_plus_tree.py
_hydrogenlib_core/data_structures/binary_tree.py
_hydrogenlib_core/data_structures/graph.py
_hydrogenlib_core/data_structures/heap.py
_hydrogenlib_core/data_structures/huffman_tree.py
_hydrogenlib_core/data_structures/stack.py
_hydrogenlib_core/data_structures/tree.py
_hydrogenlib_core/data_structures/vis_structure.py
_hydrogenlib_core/data_structures/wrappers.py
_hydrogenlib_core/fsutil/__init__.py
_hydrogenlib_core/fsutil/copy.py
_hydrogenlib_core/fsutil/dir_struct.py
_hydrogenlib_core/fsutil/file.py
_hydrogenlib_core/fsutil/hard_link.py
_hydrogenlib_core/fsutil/soft_link.py
_hydrogenlib_core/json/__init__.py
_hydrogenlib_core/json/common.py
_hydrogenlib_core/json/objective_support.py
_hydrogenlib_core/socket_methods/__init__.py
_hydrogenlib_core/socket_methods/addr.py
_hydrogenlib_core/socket_methods/async_socket.py
_hydrogenlib_core/socket_methods/socket_consts.py
_hydrogenlib_core/std_extends/__init__.py
_hydrogenlib_core/std_extends/objective_struct.py
_hydrogenlib_core/std_extends/objective_struct.pyi
_hydrogenlib_core/std_extends/rich_print.py
_hydrogenlib_core/std_extends/builtin_methods/__init__.py
_hydrogenlib_core/std_extends/builtin_methods/frozen_dict.py
_hydrogenlib_core/threading_methods/__init__.py
_hydrogenlib_core/threading_methods/methods.py
hydrogenlib_core-0.5.0.dist-info/METADATA
hydrogenlib_core-0.5.0.dist-info/WHEEL
hydrogenlib_core-0.5.0.dist-info/RECORD
