Metadata-Version: 2.4
Name: HydrogenLib-Core
Version: 0.5.0
Project-URL: Documentation, https://github.com/LittleSong2025/HydrogenLib#readme
Project-URL: Issues, https://github.com/LittleSong2025/HydrogenLib/issues
Project-URL: Source, https://github.com/LittleSong2025/HydrogenLib
Author-email: LittleNightSong <LittleNightSongYO@outlook.com>
Classifier: Development Status :: 3 - Alpha
Classifier: Programming Language :: Python
Classifier: Programming Language :: Python :: 3.11
Classifier: Programming Language :: Python :: 3.12
Classifier: Programming Language :: Python :: 3.13
Classifier: Programming Language :: Python :: Implementation :: CPython
Classifier: Programming Language :: Python :: Implementation :: PyPy
Requires-Python: >=3.12
Requires-Dist: aiofiles>=24.1.0
Requires-Dist: anyio>=4.11.0
Requires-Dist: asyncstdlib>=3.13.1
Requires-Dist: bitarray~=3.0
Requires-Dist: jsonpickle~=3.3
Requires-Dist: ping3~=4.0
Requires-Dist: psutil~=6.0
Requires-Dist: rich~=14.0
